iquail/__init__.py
iquail/constants.py
iquail/errors.py
iquail/manager.py
iquail/run.py
iquail/side_img.gif
iquail/builder/__init__.py
iquail/builder/builder.py
iquail/builder/builder_action.py
iquail/builder/cmd_base.py
iquail/builder/cmd_icon.py
iquail/builder/cmd_integrity.py
iquail/builder/cmd_noconsole.py
iquail/builder/cmd_zip.py
iquail/controller/__init__.py
iquail/controller/controller_base.py
iquail/controller/controller_console.py
iquail/controller/controller_tkinter/__init__.py
iquail/controller/controller_tkinter/controller.py
iquail/controller/controller_tkinter/error_reporter.py
iquail/controller/controller_tkinter/frames.py
iquail/helper/__init__.py
iquail/helper/configuration.py
iquail/helper/file_ignore.py
iquail/helper/integrity_verifier.py
iquail/helper/linux_polkit_file.py
iquail/helper/misc.py
iquail/helper/traceback_info.py
iquail/installer/__init__.py
iquail/installer/installer.py
iquail/installer/installer_base.py
iquail/installer/installer_linux.py
iquail/installer/installer_windows.py
iquail/solution/__init__.py
iquail/solution/solution_base.py
iquail/solution/solution_ftp.py
iquail/solution/solution_github.py
iquail/solution/solution_local.py
iquail/solution/solution_packed.py
iquail/solution/solution_zip.py
iquail/solution/solutioner.py
iquail/validate/__init__.py
iquail/validate/validate.py
iquail-2.0.dist-info/LICENSE
iquail-2.0.dist-info/METADATA
iquail-2.0.dist-info/WHEEL
iquail-2.0.dist-info/top_level.txt
iquail-2.0.dist-info/RECORD
