Metadata-Version: 2.1
Name: iquail
Version: 2.0
Summary: iQuail cross-platform installer
Home-page: https://github.com/QuailTeam/iQuail
Author: Quail team
Author-email: quail_2020@labeip.epitech.eu
License: UNKNOWN
Keywords: tool,deploy,installer,wizard,install,update,quail
Platform: UNKNOWN
Classifier: Intended Audience :: Developers
Classifier: Development Status :: 4 - Beta
Classifier: Programming Language :: Python :: 3 :: Only
Classifier: Topic :: Software Development
Requires-Dist: pyinstaller
Requires-Dist: Pillow
Requires-Dist: pypiwin32 ; sys_platform == "win32"
